divsufsort.cp39-win_amd64.pyd
divsufsort-1.0.1.dist-info/LICENSE
divsufsort-1.0.1.dist-info/METADATA
divsufsort-1.0.1.dist-info/WHEEL
divsufsort-1.0.1.dist-info/top_level.txt
divsufsort-1.0.1.dist-info/RECORD
