Metadata-Version: 2.1
Name: divsufsort
Version: 1.0.1
Summary: Python bindings for libdivsufsort
Home-page: https://github.com/avast/divsufsort-python
Author: Martin Vejnár
Author-email: martin.vejnar@avast.com
License: MIT
Platform: UNKNOWN
